ShopiPy.py
shopi_py-1.0.4.dist-info/LICENSE
shopi_py-1.0.4.dist-info/METADATA
shopi_py-1.0.4.dist-info/WHEEL
shopi_py-1.0.4.dist-info/top_level.txt
shopi_py-1.0.4.dist-info/RECORD
