Metadata-Version: 2.1
Name: shopi-py
Version: 1.0.4
Summary: An unnofical python package to interact with shopify stores
Home-page: https://github.com/ArnavChawla/Python-Shopify
Author: Arnav Chawla
Author-email: arnavchawla23@gmail.com
License: UNKNOWN
Platform: UNKNOWN
Classifier: License :: OSI Approved :: MIT License
Requires-Dist: RequestSoup
